serializer/VERSION
serializer/__init__.py
serializer/_core.py
serializer/_serializer.py
tests/__init__.py
tests/test_serialiser.py
py_serializer-0.9.6.dist-info/LICENSE
py_serializer-0.9.6.dist-info/METADATA
py_serializer-0.9.6.dist-info/WHEEL
py_serializer-0.9.6.dist-info/top_level.txt
py_serializer-0.9.6.dist-info/RECORD
