Metadata-Version: 2.1
Name: py-serializer
Version: 0.9.6
Summary: Package for serializing python object & dataclasses
Home-page: UNKNOWN
Author: Hamilakis Nicolas
Author-email: nick.hamilakis562@gmail.com
License: UNKNOWN
Platform: UNKNOWN
Classifier: Development Status :: 4 - Beta
Classifier: License :: OSI Approved :: MIT License
Classifier: Programming Language :: Python :: 3
Classifier: Programming Language :: Python :: 3.6
Classifier: Programming Language :: Python :: 3.7
Classifier: Programming Language :: Python :: 3.8
Classifier: Typing :: Typed
